Workbook

Sheet Summary
A1: SANDCASTLE / MYRTLE BEACH RADISSON — BRIDGE LOAN PACKAGE
A2: Prepared under Mosaic Capital Solutions
A4: Property | B4: 150-key oceanfront hotel, Myrtle Beach SC | C4: Bridge memo p.1
A5: Flag (post-conversion) | B5: Radisson (Choice Hotels) | C5: Bridge memo
A6: Sponsor | B6: Laray Benton | C6: Bridge memo
A7: Purchase Price | B7: 16500000 | C7: PSA per bridge memo
A8: 2022 Appraised Value | B8: 23000000 | C8: Appraisal 22-NY-454
A9: Discount to Appraisal | B9: =1-B7/B8 | C9: = 1 - price / appraisal
A10: Total Project Cost | B10: 25000000 | C10: Sources & Uses sheet
A11: Loan Request (Senior Bridge) | B11: 18400000 | C11: Bridge memo
A12: LTC | B12: =B11/B10 | C12: = loan / total cost
A13: LTV on 2022 Appraisal | B13: =B11/B8 | C13: = loan / appraisal
A14: Price per Key | B14: =B7/150 | C14: = price / keys
A15: Stabilized DSCR (Y3) | B15: ='Debt & Covenants'!B14 | C15: Debt sheet
A16: Stabilized Debt Yield (Y3) | B16: ='Debt & Covenants'!B15 | C16: Debt sheet

Sheet Sources & Uses
A1: SOURCES | B1: Amount | C1: % Total | D1: Notes
A2: Senior Bridge Loan | B2: 18400000 | C2: =B2/$B$7 | D2: Single unitranche, first lien
A3: Sponsor Equity (invested) | B3: 6500000 | C3: =B3/$B$7 | D3: Predevelopment, deposit, soft costs, closing gap
A4: Seller Carry Note | B4: 2000000 | C4: =B4/$B$7 | D4: 5-yr, 6%, fully subordinated
A5: Additional Equity Raise | B5: 1600000 | C5: =B5/$B$7 | D5: LP or capital call at close
A6: Key Money (Choice, at PIP completion) | B6: 2500000 | C6: =B6/$B$7 | D6: Earned Month 20-21, treated as equity; NOT cash at close
A7: Total Sources (at-close basis excl. key money) | B7: =SUM(B2:B5) | D7: Memo presents 25MM incl. key money; at-close cash = 28.5-2.5+contra
A9: USES | B9: Amount | C9: % Total | D9: Notes
A10: Property Acquisition | B10: 16500000 | C10: =B10/$B$15 | D10: Purchase price
A11: Renovation / PIP | B11: 8500000 | C11: =B11/$B$15 | D11: Phased draws, months 1-20
A12: Closing Costs | B12: 750000 | C12: =B12/$B$15 | D12: Legal, DD, title, lender fees
A13: Reserves | B13: 1250000 | C13: =B13/$B$15 | D13: DS reserve 700K, op deficit 500K, replacement 50K
A14: Working Capital | B14: 500000 | C14: =B14/$B$15 | D14: Pre-opening, marketing, staffing
A15: Total Uses | B15: =SUM(B10:B14)
A17: Check: Uses 25.0MM vs Sources incl. key money 31.0MM per memo tables; memo double counts. At-close sources 28.5MM excl. key money = uses 27.5? See Audit sheet variance log.

Sheet Operating Pro Forma
B1: Y1 Renovation | C1: Y2 Stabilizing | D1: Y3 Stabilized | E1: Source / Formula
A2: Keys | B2: 150 | C2: 150 | D2: 150 | E2: Bridge memo
A3: Occupancy | B3: 0.3 | C3: 0.62 | D3: 0.7 | E3: Memo pro forma assumptions
A4: ADR | B4: 110 | C4: 150 | D4: 160 | E4: Memo pro forma assumptions
A5: RevPAR | B5: =B3*B4 | C5: =C3*C4 | D5: =D3*D4 | E5: = occupancy x ADR
A6: Rooms Revenue | B6: =B2*365*B3*B4 | C6: =C2*365*C3*C4 | D6: =D2*365*D3*D4 | E6: = keys x 365 x occ x ADR
A7: F&B / Ancillary | B7: 12750 | C7: 800000 | D7: 975000 | E7: Memo (Y1 est to reconcile total rev)
A8: Total Revenue | B8: =B6+B7 | C8: =C6+C7 | D8: =D6+D7 | E8: = rooms + ancillary
A9: Operating Expenses | B9: 1400000 | C9: 3685000 | D9: 4264000 | E9: Memo; Y2 ~62%, Y3 ~60% of revenue
A10: Expense Ratio | B10: =B9/B8 | C10: =C9/C8 | D10: =D9/D8 | E10: = expenses / revenue
A11: NOI | B11: =B8-B9 | C11: =C8-C9 | D11: =D8-D9 | E11: = revenue - expenses
A13: Memo variance note: memo states Y2 rooms revenue 5,115,750 and Y3 6,132,000; formula math gives the values above. Formulas govern.

Sheet Debt & Covenants
A1: Facility
A2: Loan Amount | B2: 18400000 | C2: Single unitranche, first lien
A3: Index (SOFR) | B3: 0.053 | C3: Memo, current SOFR ~5.30% (Dec 2025). REFRESH AT SUBMISSION
A4: Spread (bps) | B4: 400 | C4: Target SOFR + 350-400; conservative end used
A5: All-in Rate | B5: =B3+B4/10000 | C5: = index + spread
A6: Amortization | B6: Interest-only months 1-26 | C6: Memo
A7: Annual Debt Service (IO) | B7: =B2*B5 | C7: = loan x all-in rate
A8: Origination Fee (2.0%) | B8: =B2*0.02 | C8: Memo range 1.5-2.0%
A9: Exit Fee (1.0% if < 24 mo) | B9: =B2*0.01 | C9: Waived if held 30+ months
A11: Coverage | B11: Value | C11: Test
A12: Y1 DSCR | B12: ='Operating Pro Forma'!B11/B7 | C12: Covered by DS reserve + sponsor carry guaranty
A13: Y2 DSCR | B13: ='Operating Pro Forma'!C11/B7 | C13: Covenant min 1.25x at stabilization (Month 26+)
A14: Y3 DSCR | B14: ='Operating Pro Forma'!D11/B7 | C14: Covenant min 1.25x
A15: Y3 Debt Yield | B15: ='Operating Pro Forma'!D11/B2 | C15: Covenant min 10.0%
A16: Occupancy covenant | B16: 0.6 | C16: Min 60% for 90 consecutive days post-renovation
A17: ADR covenant | B17: 140 | C17: Min $140 average post-renovation
A19: Reserves
A20: Debt Service Reserve | B20: 700000 | C20: 6 months interest, funded at closing
A21: Operating Deficit Reserve | B21: 500000 | C21: Released at DSCR > 1.15x two consecutive quarters
A22: Replacement Reserve | B22: =150*300 | C22: $300/key/year

Sheet Sensitivity
A1: Y3 DSCR: Occupancy x ADR | B1: ADR 140 | C1: ADR 150 | D1: ADR 160 | E1: ADR 170
A2: Occ 60% | B2: =((150*365*0.6*140+'Operating Pro Forma'!$D$7)*(1-0.60))/'Debt & Covenants'!$B$7 | C2: =((150*365*0.6*150+'Operating Pro Forma'!$D$7)*(1-0.60))/'Debt & Covenants'!$B$7 | D2: =((150*365*0.6*160+'Operating Pro Forma'!$D$7)*(1-0.60))/'Debt & Covenants'!$B$7 | E2: =((150*365*0.6*170+'Operating Pro Forma'!$D$7)*(1-0.60))/'Debt & Covenants'!$B$7
A3: Occ 65% | B3: =((150*365*0.65*140+'Operating Pro Forma'!$D$7)*(1-0.60))/'Debt & Covenants'!$B$7 | C3: =((150*365*0.65*150+'Operating Pro Forma'!$D$7)*(1-0.60))/'Debt & Covenants'!$B$7 | D3: =((150*365*0.65*160+'Operating Pro Forma'!$D$7)*(1-0.60))/'Debt & Covenants'!$B$7 | E3: =((150*365*0.65*170+'Operating Pro Forma'!$D$7)*(1-0.60))/'Debt & Covenants'!$B$7
A4: Occ 70% | B4: =((150*365*0.7*140+'Operating Pro Forma'!$D$7)*(1-0.60))/'Debt & Covenants'!$B$7 | C4: =((150*365*0.7*150+'Operating Pro Forma'!$D$7)*(1-0.60))/'Debt & Covenants'!$B$7 | D4: =((150*365*0.7*160+'Operating Pro Forma'!$D$7)*(1-0.60))/'Debt & Covenants'!$B$7 | E4: =((150*365*0.7*170+'Operating Pro Forma'!$D$7)*(1-0.60))/'Debt & Covenants'!$B$7
A5: Occ 75% | B5: =((150*365*0.75*140+'Operating Pro Forma'!$D$7)*(1-0.60))/'Debt & Covenants'!$B$7 | C5: =((150*365*0.75*150+'Operating Pro Forma'!$D$7)*(1-0.60))/'Debt & Covenants'!$B$7 | D5: =((150*365*0.75*160+'Operating Pro Forma'!$D$7)*(1-0.60))/'Debt & Covenants'!$B$7 | E5: =((150*365*0.75*170+'Operating Pro Forma'!$D$7)*(1-0.60))/'Debt & Covenants'!$B$7
A7: Assumes Y3 ancillary revenue and a 60% expense ratio; debt service from Debt sheet.

Sheet Refinance & Exit
A1: Permanent Debt Sizing (Month 30-36)
A2: Stabilized NOI (Y3) | B2: ='Operating Pro Forma'!D11 | C2: Pro forma sheet
A3: Perm Rate | B3: 0.065 | C3: Memo assumption
A4: Perm Amortization (years) | B4: 30 | C4: Memo assumption
A5: Loan Constant | B5: =(B3/12*POWER(1+B3/12,B4*12))/(POWER(1+B3/12,B4*12)-1)*12 | C5: Monthly payment constant, annualized
A6: Min DSCR Sizing (1.30x) | B6: =B2/1.3/B5 | C6: = NOI / 1.30 / constant
A7: Exit Cap Rate | B7: 0.08 | C7: Memo assumption
A8: Stabilized Value | B8: =B2/B7 | C8: = NOI / cap
A9: 65% LTV Sizing | B9: =B8*0.65 | C9: = value x 65%
A10: Conservative Proceeds (lower of) | B10: =MIN(B6,B9) | C10: Lower of DSCR and LTV sizing
A11: Senior Bridge Payoff | B11: ='Debt & Covenants'!B2
A12: Refi Closing Costs | B12: 350000 | C12: Memo
A13: Cash to Equity at Refi | B13: =B10-B11-B12 | C13: = proceeds - payoff - costs

Sheet Audit
A1: Item | B1: Note | C1: Confidence
A2: Source document | B2: Myrtle_Beach_Radisson_Bridge_Financing_Memo.md, Dec 8 2025, authored by Russ | C2: 0.9
A3: Appraisal | B3: 22-NY-454 Sandcastle South Beach (2022, 23.0MM). Dated; lender will re-appraise | C3: 0.7
A4: SOFR 5.30% | B4: As of memo date Dec 2025. Must refresh at submission | C4: 0.5
A5: Y2 rooms revenue variance | B5: Memo table says 5,115,750; keys x 365 x 62% x 150 = 5,092,875. Formula governs | C5: 1
A6: Y3 rooms revenue variance | B6: Memo says 6,132,000; keys x 365 x 70% x 160 = 6,132,000. Matches | C6: 1
A7: Sources table variance | B7: Memo sources sum to 31.0MM against 25.0MM uses because key money and seller carry both listed at close; key money lands Month 20-21 | C7: 1
A8: Y1 F&B plug | B8: Y1 ancillary set to reconcile memo total revenue 1,815,000 with rooms formula | C8: 0.6
A9: Trailing financials | B9: T12 occupancy 52%, ADR 118, RevPAR 61 per memo. No operating statements in data room yet: REQUEST | C9: 0.5
